[{"name":{"common":"Liechtenstein","official":"Principality of Liechtenstein","nativeName":{"deu":{"official":"Fürstentum Liechtenstein","common":"Liechtenstein"}}},"tld":[".li"],"cca2":"LI","ccn3":"438","cca3":"LIE","cioc":"LIE","independent":true,"status":"officially-assigned","unMember":true,"currencies":{"CHF":{"name":"Swiss franc","symbol":"Fr"}},"idd":{"root":"+4","suffixes":["23"]},"capital":["Vaduz"],"altSpellings":["LI","Principality of Liechtenstein","Fürstentum Liechtenstein"],"region":"Europe","subregion":"Western Europe","languages":{"deu":"German"},"translations":{"ara":{"official":"إمارة ليختنشتاين","common":"ليختنشتاين"},"ces":{"official":"Knížectví Lichtenštejnské","common":"Lichtenštejnsko"},"cym":{"official":"Principality of Liechtenstein","common":"Liechtenstein"},"deu":{"official":"Fürstentum Liechtenstein","common":"Liechtenstein"},"est":{"official":"Liechtensteini Vürstiriik","common":"Liechtenstein"},"fin":{"official":"Liechensteinin ruhtinaskunta","common":"Liechenstein"},"fra":{"official":"Principauté du Liechtenstein","common":"Liechtenstein"},"hrv":{"official":"Kneževina Lihtenštajn","common":"Lihtenštajn"},"hun":{"official":"Liechtensteini Hercegség","common":"Liechtenstein"},"ita":{"official":"Principato del Liechtenstein","common":"Liechtenstein"},"jpn":{"official":"リヒテンシュタイン公国","common":"リヒテンシュタイン"},"kor":{"official":"리히텐슈타인 공국","common":"리히텐슈타인"},"nld":{"official":"Vorstendom Liechtenstein","common":"Liechtenstein"},"per":{"official":"شاهزاده‌نشین لیختن‌اشتاین","common":"لیختن‌اشتاین"},"pol":{"official":"Księstwo Liechtensteinu","common":"Liechtenstein"},"por":{"official":"Principado de Liechtenstein","common":"Liechtenstein"},"rus":{"official":"Княжество Лихтенштейн","common":"Лихтенштейн"},"slk":{"official":"Lichtenštajnské kniežatstvo","common":"Lichtenštajnsko"},"spa":{"official":"Principado de Liechtenstein","common":"Liechtenstein"},"swe":{"official":"Furstendömet Liechtenstein","common":"Liechtenstein"},"urd":{"official":"امارات لیختینستائن","common":"لیختینستائن"},"zho":{"official":"列支敦士登公国","common":"列支敦士登"}},"latlng":[47.26666666,9.53333333],"landlocked":true,"borders":["AUT","CHE"],"area":160.0,"demonyms":{"eng":{"f":"Liechtensteiner","m":"Liechtensteiner"},"fra":{"f":"Liechtensteinoise","m":"Liechtensteinois"}},"flag":"\uD83C\uDDF1\uD83C\uDDEE","maps":{"googleMaps":"https://goo.gl/maps/KNuHeiJzAPodwM7y6","openStreetMaps":"https://www.openstreetmap.org/relation/1155955"},"population":38137,"fifa":"LIE","car":{"signs":["FL"],"side":"right"},"timezones":["UTC+01:00"],"continents":["Europe"],"flags":{"png":"https://flagcdn.com/w320/li.png","svg":"https://flagcdn.com/li.svg"},"coatOfArms":{"png":"https://mainfacts.com/media/images/coats_of_arms/li.png","svg":"https://mainfacts.com/media/images/coats_of_arms/li.svg"},"startOfWeek":"monday","capitalInfo":{"latlng":[47.13,9.52]},"postalCode":{"format":"####","regex":"^(\\d{4})$"}},{"name":{"common":"Switzerland","official":"Swiss Confederation","nativeName":{"fra":{"official":"Confédération suisse","common":"Suisse"},"gsw":{"official":"Schweizerische Eidgenossenschaft","common":"Schweiz"},"ita":{"official":"Confederazione Svizzera","common":"Svizzera"},"roh":{"official":"Confederaziun svizra","common":"Svizra"}}},"tld":[".ch"],"cca2":"CH","ccn3":"756","cca3":"CHE","cioc":"SUI","independent":true,"status":"officially-assigned","unMember":true,"currencies":{"CHF":{"name":"Swiss franc","symbol":"Fr."}},"idd":{"root":"+4","suffixes":["1"]},"capital":["Bern"],"altSpellings":["CH","Swiss Confederation","Schweiz","Suisse","Svizzera","Svizra"],"region":"Europe","subregion":"Western Europe","languages":{"fra":"French","gsw":"Swiss German","ita":"Italian","roh":"Romansh"},"translations":{"ara":{"official":"الاتحاد السويسري","common":"سويسرا"},"ces":{"official":"Švýcarská konfederace","common":"Švýcarsko"},"cym":{"official":"Swiss Confederation","common":"Switzerland"},"deu":{"official":"Schweizerische Eidgenossenschaft","common":"Schweiz"},"est":{"official":"Šveitsi Konföderatsioon","common":"Šveits"},"fin":{"official":"Sveitsin valaliitto","common":"Sveitsi"},"fra":{"official":"Confédération suisse","common":"Suisse"},"hrv":{"official":"švicarska Konfederacija","common":"Švicarska"},"hun":{"official":"Svájc","common":"Svájc"},"ita":{"official":"Confederazione svizzera","common":"Svizzera"},"jpn":{"official":"スイス連邦","common":"スイス"},"kor":{"official":"스위스 연방","common":"스위스"},"nld":{"official":"Zwitserse Confederatie","common":"Zwitserland"},"per":{"official":"کنفدراسیون سوئیس","common":"سوئیس"},"pol":{"official":"Konfederacja Szwajcarska","common":"Szwajcaria"},"por":{"official":"Confederação Suíça","common":"Suíça"},"rus":{"official":"Швейцарская Конфедерация","common":"Швейцария"},"slk":{"official":"Švajčiarska konfederácia","common":"Švajčiarsko"},"spa":{"official":"Confederación Suiza","common":"Suiza"},"swe":{"official":"Schweiziska edsförbundet","common":"Schweiz"},"urd":{"official":"سوئیس  متحدہ","common":"سویٹذرلینڈ"},"zho":{"official":"瑞士联邦","common":"瑞士"}},"latlng":[47.0,8.0],"landlocked":true,"borders":["AUT","FRA","ITA","LIE","DEU"],"area":41284.0,"demonyms":{"eng":{"f":"Swiss","m":"Swiss"},"fra":{"f":"Suisse","m":"Suisse"}},"flag":"\uD83C\uDDE8\uD83C\uDDED","maps":{"googleMaps":"https://goo.gl/maps/uVuZcXaxSx5jLyEC9","openStreetMaps":"https://www.openstreetmap.org/relation/51701"},"population":17500657,"gini":{"2018":33.1},"fifa":"SUI","car":{"signs":["CH"],"side":"right"},"timezones":["UTC+01:00"],"continents":["Europe"],"flags":{"png":"https://flagcdn.com/w320/ch.png","svg":"https://flagcdn.com/ch.svg"},"coatOfArms":{"png":"https://mainfacts.com/media/images/coats_of_arms/ch.png","svg":"https://mainfacts.com/media/images/coats_of_arms/ch.svg"},"startOfWeek":"monday","capitalInfo":{"latlng":[46.92,7.47]},"postalCode":{"format":"####","regex":"^(\\d{4})$"}}]